amsdal_glue_api_server/__about__.py
amsdal_glue_api_server/__init__.py
amsdal_glue_api_server/app.py
amsdal_glue_api_server/py.typed
amsdal_glue_api_server/routes.py
amsdal_glue_api_server/controllers/__init__.py
amsdal_glue_api_server/controllers/operations/__init__.py
amsdal_glue_api_server/controllers/operations/data_commands.py
amsdal_glue_api_server/controllers/operations/models.py
amsdal_glue_api_server/controllers/operations/query_commands.py
amsdal_glue_api_server/controllers/operations/schema_commands.py
amsdal_glue_api_server/controllers/operations/transaction_commands.py
amsdal_glue_api_server/controllers/rest/__init__.py
amsdal_glue_api_server/controllers/rest/create_controller.py
amsdal_glue_api_server/controllers/rest/delete_controller.py
amsdal_glue_api_server/controllers/rest/list_controller.py
amsdal_glue_api_server/controllers/rest/update_controller.py
amsdal_glue_api_server/controllers/sql/__init__.py
amsdal_glue_api_server/controllers/sql/sql.py
amsdal_glue_api_server-0.1.1.dist-info/METADATA
amsdal_glue_api_server-0.1.1.dist-info/WHEEL
amsdal_glue_api_server-0.1.1.dist-info/licenses/LICENSE.txt
amsdal_glue_api_server-0.1.1.dist-info/RECORD
