Metadata-Version: 2.4
Name: amsdal-glue-api-server
Version: 0.1.1
Summary: AMSDAL Glue API Server is a web API interface over AMSDAL Glue, providing high-level abstraction for interacting with multiple databases simultaneously over HTTP
Project-URL: Documentation, https://github.com/amsdal/amsdal-glue?tab=readme-ov-file#amsdal-glue-project
Project-URL: Issues, https://github.com/amsdal/amsdal-glue/issues
Project-URL: Source, https://github.com/amsdal/amsdal-glue/
License:                                  Apache License
License-File: LICENSE.txt
Classifier: Development Status :: 4 - Beta
Classifier: Programming Language :: Python
Classifier: Programming Language :: Python :: 3.10
Classifier: Programming Language :: Python :: 3.11
Classifier: Programming Language :: Python :: Implementation :: CPython
Classifier: Programming Language :: Python :: Implementation :: PyPy
Requires-Python: >=3.10
Requires-Dist: amsdal-glue-sql-parser[sqloxide]>=0.1.0
Requires-Dist: amsdal-glue>=0.1.0
Requires-Dist: fastapi>=0.111.1
Requires-Dist: uvicorn>=0.30.3
